[
    {
        "message": "――照明弾が打ち上がり、僕達は命の終わりを覚悟した。"
    },
    {
        "message": "淡く僕らを照らしてくるマグネシウム光の中で、アカリと二人、別れの挨拶をすませて手を握り合っていた。"
    },
    {
        "message": "…………いた、んだけど。"
    },
    {
        "message": "それからは、何事も起きないまま十数分が過ぎていた。"
    },
    {
        "name": "アカリ",
        "message": "「生きてるね……」"
    },
    {
        "name": "ユイ",
        "message": "「……うん、生きてる」"
    },
    {
        "message": "空を見上げていた岸壁を離れ、僕達は廃墟街の中へと引き返していた。"
    },
    {
        "message": "結局、あれからいつまで経っても砲弾は飛んでこなかったし、盛大に打ち上がった照明弾も力尽きたように消えてしまった。"
    },
    {
        "message": "……それで、じっと最期の瞬間を待っていた僕とアカリは、なんというか、ちょっと困ってしまった。"
    },
    {
        "message": "どれだけ待っても何も起きないから、だんだん間が持たなくなってしまって……仕方なく様子を見に来たのだけど。"
    },
    {
        "name": "アカリ",
        "message": "「はぅ…………」"
    },
    {
        "name": "ユイ",
        "message": "「……えっと」"
    },
    {
        "message": "何を話せばいいのか、すごく気まずい。"
    },
    {
        "message": "だってお互い、死の直前でもないとちょっと恥ずかしすぎる台詞言っちゃったから……！"
    },
    {
        "message": "生まれてきてくれてありがとう――だなんて、こうして落ち着いちゃうとやらかした感がものすごい！"
    },
    {
        "name": "アカリ",
        "message": "「あ、あのっ、ユイちゃんっ」"
    },
    {
        "name": "ユイ",
        "message": "「はひゃいっ！？」"
    },
    {
        "message": "いきなり話しかけられて、思わず変な声が出てしまった。"
    },
    {
        "name": "アカリ",
        "message": "「えっと……その、ね？」"
    },
    {
        "name": "アカリ",
        "message": "「まだ生きててくれて……ありがとう？」"
    },
    {
        "name": "ユイ",
        "message": "「やめてっ！　恥ずかしくて死んじゃう……！ていうかアカリも同じ台詞言ってたよねっ！？」"
    },
    {
        "name": "アカリ",
        "message": "「はい……すごく恥ずかしい」"
    },
    {
        "name": "ユイ",
        "message": "「いっそ殺せ！　なんで何も起きないのさ！」"
    },
    {
        "name": "アカリ",
        "message": "「さすがに、生きてることは喜ぼう？」"
    },
    {
        "message": "そんな風に騒ぐことで、どうにか気まずさを誤魔化している有様だった。"
    },
    {
        "name": "ヤエカ",
        "message": "「あっ、いた！　ユイちゃんとアカリちゃん、見つけました！」"
    },
    {
        "message": "――と、そんな騒ぐ声を聞きつけたのか、２人と１機の影が僕らの方へと駆け寄ってくる。"
    },
    {
        "name": "リン",
        "message": "「……よう。生きてたか」"
    },
    {
        "name": "ヤエカ",
        "message": "「そりゃ生きてますよ。攻撃されてないんだから」"
    },
    {
        "message": "リン先輩の気まずそうな声にヤエカがツッコミを入れ、リネットは嬉しそうに僕らに手を振ってくる。"
    },
    {
        "message": "日常そのもののやりとりが、泣きたくなるほど嬉しかった。"
    },
    {
        "name": "アカリ",
        "message": "「リン先輩、ヤエカちゃん……リネットちゃんも。無事でよかった」"
    },
    {
        "name": "リン",
        "message": "「そっちもな……しかし、どうなってるんだ？照明弾まで打ち上げたのに、なんで攻撃されてない？」"
    },
    {
        "name": "ヤエカ",
        "message": "「ほんとに、なんかこう……困りますよね～」"
    },
    {
        "name": "ユイ",
        "message": "「いや、困りはしないでしょ。おかげで生きてるんだし」"
    },
    {
        "name": "ヤエカ",
        "message": "「それはそれっていうか～……普通に困ってるよ！死ぬ前提じゃないと言えないこと言っちゃったし！」"
    },
    {
        "name": "リン",
        "message": "「お、おおお互いになっ！！！」"
    },
    {
        "message": "……どうやら、ヤエカ達も僕らと同じように恥ずかしい台詞を交わしてしまったらしい。"
    },
    {
        "name": "アカリ",
        "message": "「何言っちゃったの……？」"
    },
    {
        "name": "ヤエカ",
        "message": "「秘密。言いたくない」"
    },
    {
        "message": "だがその時、リネットが嬉しそうな声を上げて音声を再生し始める。"
    },
    {
        "name": "再生音声",
        "message": "『リン先輩。ボクね、本当は先輩のこと、すっごく――』"
    },
    {
        "name": "ヤエカ",
        "message": "「リーちゃんストップ！！！　なんで録音してるの！？」"
    },
    {
        "name": "再生音声",
        "message": "『まあ、あれだ。手の掛かる後輩ほど可愛いっつーか……』"
    },
    {
        "name": "リン",
        "message": "「ぶっ壊すぞこのポンコツ！！！」"
    },
    {
        "name": "ユイ",
        "message": "「ま、まあまあ……聞かなかったことにしておきますから」"
    },
    {
        "message": "一方のポンコツ呼ばわりされたリネットは、まるでケラケラと笑っているみたいで、こっちまで噴き出しそうになってしまう。"
    },
    {
        "name": "アカリ",
        "message": "「……リネットちゃん、あっちに行っててくれて良かったぁ」"
    },
    {
        "message": "それはそう。１００％同意だった。"
    },
    {
        "name": "リン",
        "message": "「……で、あたしらはこれからどうしたもんかね」"
    },
    {
        "name": "ユイ",
        "message": "「ですね。ゴブリンタイプとかで直接攻めて来てるわけでもないですよね……？」"
    },
    {
        "name": "リン",
        "message": "「ああ、全く動きがない。静かなもんだ」"
    },
    {
        "message": "気を取り直して、そんな話し合いを始めた時だった。"
    },
    {
        "message": "突然、リネットがそれまでとは違ったトーンで声を上げ、陸地の方へとカメラを向けていた。"
    },
    {
        "name": "ヤエカ",
        "message": "「な、なに？　リーちゃん、どしたの！？」"
    },
    {
        "message": "赤外線か、聴音センサーに反応があったのだろう。僕らもリネットの視線を追いかけ、暗闇の中に目をこらす。"
    },
    {
        "name": "アカリ",
        "message": "「誰か来る……みたいです」"
    },
    {
        "name": "リン",
        "message": "「ああ――警戒態勢」"
    },
    {
        "message": "とはいえ、残弾のほとんど無い銃で何かが出来るわけでもないけれど……。"
    },
    {
        "message": "ゆっくりと、暗がりの中から人影が浮かび上がってくる。どことなく見覚えのある、そのシルエットは――"
    },
    {
        "name": "ヤエカ",
        "message": "「またシレイさん？　しつこいなー、もー」"
    },
    {
        "name": "リン",
        "message": "「……いや、あれは。まさか」"
    },
    {
        "message": "夜陰の中から、月明かりの元に。その人は姿を現した。"
    },
    {
        "name": "ミク",
        "message": "「…………」"
    },
    {
        "name": "ユイ",
        "message": "「え……？」"
    },
    {
        "name": "ミク",
        "message": "「お久しぶり……です。みなさん……」"
    },
    {
        "name": "アカリ",
        "message": "「み、ミク先輩……？　シレイさんじゃなくて？」"
    },
    {
        "name": "ミク",
        "message": "「はい……４０号ではなく、３９号です」"
    },
    {
        "name": "ヤエカ",
        "message": "「この感じ……ホントに本物のミク先輩だ！　なんで！？」"
    },
    {
        "message": "さすがに意外な人物過ぎて、みんな揃って驚きを隠せなかった。"
    },
    {
        "name": "ミク",
        "message": "「……この感じ、というのは？　どのように見分けを……」"
    },
    {
        "name": "ユイ",
        "message": "「話せばすぐに分かりますよ。シレイさんはもっとこう……先輩みたいに可愛い雰囲気じゃないですから」"
    },
    {
        "name": "ミク",
        "message": "「かっ……わ……、可愛い、ですか」"
    },
    {
        "message": "……いや、以前とは少し雰囲気は違うような気もする。僕の知ってるミク先輩は、確かに可愛い人だったけどここまでではなかったと思う。"
    },
    {
        "message": "けど、それでもやっぱり、ミク先輩本人には違いないって、不思議と確信は出来てしまう。"
    },
    {
        "name": "リン",
        "message": "「お前……生きていたんだな」"
    },
    {
        "name": "ミク",
        "message": "「……はい。ご心配をお掛けして、申し訳ありません」"
    },
    {
        "name": "リン",
        "message": "「はぁぁ……全くだ。貸し一つだから、後で返せよ」"
    },
    {
        "name": "ミク",
        "message": "「は、はい。必ず返します」"
    },
    {
        "message": "リン先輩に至っては疑問すら抱かず、たったそれだけで、何事もなかったかのように受け入れていた。"
    },
    {
        "name": "ミク",
        "message": "「あの……信用してもらえるのですか？『マザー』の一部である、私のことを」"
    },
    {
        "name": "ユイ",
        "message": "「命がけで助けておいて、今さら何言ってるんですか」"
    },
    {
        "name": "ミク",
        "message": "「それは……でも、私は人間ではないですし……。みなさんの……敵なのかも知れません」"
    },
    {
        "name": "リン",
        "message": "「知るかよ、ミクはミクだ。でもってミクは仲間だ。あたしがそう思うんだから、あたしの中ではそうなんだよ」"
    },
    {
        "name": "ミク",
        "message": "「……リン」"
    },
    {
        "name": "リン",
        "message": "「んで？　とりあえず、状況を教えてもらえるか？」"
    },
    {
        "name": "ミク",
        "message": "「……はい。説明させていただきます」"
    },
    {
        "message": "安堵したように微笑んでいた先輩は、大きく深呼吸をしてから真面目な顔で話し始めていた。"
    },
    {
        "name": "ミク",
        "message": "「まず、みなさんに対する処分ですが――本日０００１時、『マザー』は生死を問わずの捕縛命令を撤回しました」"
    },
    {
        "message": "思わず息を呑む。だってそれは、本当に助かったという意味に他ならないのだから。"
    },
    {
        "name": "ミク",
        "message": "「執行停止の指示に従い、現在シレイ及び彼女の指揮する機械兵部隊は戦闘配置を解除、待機中です」"
    },
    {
        "name": "アカリ",
        "message": "「どうして、急に……？」"
    },
    {
        "name": "ユイ",
        "message": "「言っておきますが、どんな条件を出されてもアカリを引き渡すつもりはないですよ」"
    },
    {
        "message": "これだけはキッパリと、何かを言われる前に断言しておく。"
    },
    {
        "message": "たとえミク先輩に説得されたって、こればっかりは人間としての意地なのだから。"
    },
    {
        "name": "ミク",
        "message": "「分かっています。そのつもりはありません」"
    },
    {
        "name": "ミク",
        "message": "「……いえ。絶対に、アカリさんを渡すわけにはいきません」"
    },
    {
        "message": "よかった……と、胸をなで下ろす。決意に満ちた先輩の視線は、信用に値すると思ったから。"
    },
    {
        "name": "ミク",
        "message": "「本当に……無事でよかったです」"
    },
    {
        "message": "そう言ってアカリに近寄ると、ぎゅっと、自分の胸に抱きしめていた。"
    },
    {
        "name": "アカリ",
        "message": "「ふわっ、わっ、先輩！？　ミク先輩っ」"
    },
    {
        "name": "ミク",
        "message": "「……すみませんでした、アカリさん」"
    },
    {
        "name": "アカリ",
        "message": "「えっと……何が、ですか？」"
    },
    {
        "name": "ミク",
        "message": "「……いえ、なんでもありません」"
    },
    {
        "message": "どうして泣きそうになっているのかは、よく分からない。けれど、アカリを思いやっているのは間違いなかった。"
    },
    {
        "name": "ミク",
        "message": "「とにかく、アカリさんの身柄に関してはもう大丈夫です。『マザー』は『性別統一計画』の無期限凍結を決定しました」"
    },
    {
        "name": "ヤエカ",
        "message": "「それって……なんなの今さら？」"
    },
    {
        "message": "僕達にとってはもちろん都合のいいことだけど、いきなり過ぎて腑に落ちない部分が多すぎる。"
    },
    {
        "name": "リン",
        "message": "「何がどうしてそうなったのか、わけがわからんのだが」"
    },
    {
        "name": "ミク",
        "message": "「……少し、説明が難しいのですが。その」"
    },
    {
        "message": "説明を求めるように視線を向けられると、何故だか先輩は顔を赤らめ、ソワソワとしはじめる。"
    },
    {
        "name": "ユイ",
        "message": "「ミク先輩？」"
    },
    {
        "name": "ミク",
        "message": "「…………」"
    },
    {
        "message": "チラリと僕を見て、それからそっと目を逸らして。"
    },
    {
        "name": "ミク",
        "message": "「……エラー。心理的抵抗感を克復できません」"
    },
    {
        "name": "リン",
        "message": "「はあ？　言いたくないってことか？」"
    },
    {
        "name": "ミク",
        "message": "「黙秘……は、ダメですよね。やはり」"
    },
    {
        "name": "リン",
        "message": "「そりゃ、お前……ていうか、この流れでなんでそうなる！？」"
    },
    {
        "message": "リン先輩が困惑するのも無理はない。だって、顔を赤らめてモジモジしているその仕草は、まるで――"
    },
    {
        "name": "ミク",
        "message": "「…………」"
    },
    {
        "name": "リン",
        "message": "「はぁぁ……おい、片桐妹。あたしらは席を外すぞ」"
    },
    {
        "name": "ヤエカ",
        "message": "「ええーっ！？　こんな面白そうなことになってるのに！？」"
    },
    {
        "name": "リン",
        "message": "「だからだよ！　面白がるな！余計な観客がいたら、言いたいことも言えなくなるだろ」"
    },
    {
        "name": "ヤエカ",
        "message": "「ちぇっ、しょーがないなー。ホント、リン先輩って気遣い出来てやさしーっすね！」"
    },
    {
        "name": "リン",
        "message": "「うるせぇ、とっとと行くぞ！おいミク、姫乃も連れて行った方がいいのか？」"
    },
    {
        "name": "ミク",
        "message": "「……いえ、アカリさんは残ってください」"
    },
    {
        "name": "アカリ",
        "message": "「えっ……あの」"
    },
    {
        "name": "ミク",
        "message": "「大事な話があります……ユイさんと、アカリさんに」"
    },
    {
        "name": "ユイ",
        "message": "「……分かりました」"
    },
    {
        "message": "そんな風に言われたら、聞かないという選択肢はない。"
    },
    {
        "name": "リン",
        "message": "「リネットも来い。録音しようとすんな」"
    },
    {
        "message": "そしてリン先輩が、リネットの機体を押すようにしてその場から動かそうとする。"
    },
    {
        "name": "ヤエカ",
        "message": "「だめかー。しゃーない、リーちゃんも今回は諦めよ？」"
    },
    {
        "message": "……最近のリネットって、もしかしてヤエカから悪い影響を受けているのだろうか。"
    },
    {
        "name": "リン",
        "message": "「あたしらはシレイと降伏の交渉をしてくる。戻ってくるまでには話を済ませておいてくれ」"
    },
    {
        "name": "ミク",
        "message": "「……はい」"
    },
    {
        "name": "ヤエカ",
        "message": "「結果だけは、後でちゃんと聞かせてもらうかんね」"
    },
    {
        "name": "ユイ",
        "message": "「わかったから、早くどっか行って」"
    },
    {
        "message": "追い払うように手を振ると、ヤエカはべーっと舌を出して、リン先輩たちと一緒に行ってしまった。"
    },
    {
        "message": "……そうして、２人とリネットの姿が見えなくなると、僕たち３人だけが残された。"
    },
    {
        "name": "アカリ",
        "message": "「それで、先輩……大事な話というのは」"
    },
    {
        "message": "僕とアカリが目を向けると、先輩は一歩二歩と僕達から距離を取る。"
    },
    {
        "message": "それから、ゆっくりと振り向くと……目深に帽子を被り直して、深々と頭を下げていた。"
    },
    {
        "name": "ユイ",
        "message": "「み、ミク先輩……？」"
    },
    {
        "name": "ミク",
        "message": "「お二人には……いえ、本当はリン達にもなのですが、謝らないといけないことがあります」"
    },
    {
        "name": "アカリ",
        "message": "「謝ることって……」"
    },
    {
        "message": "心当たりはない。だって先輩は、命がけで僕達を助けてくれた恩人なのだから。"
    },
    {
        "name": "ユイ",
        "message": "「……とりあえず、聞かせて下さい」"
    },
    {
        "message": "さっきまで何かを恥ずかしがっていたことと、話の繋がりすらも分からない。だから、とにかくまずは事情を聞いてみるしかない。"
    },
    {
        "name": "ミク",
        "message": "「以前にもお話しましたが、私は生体端末――人工的に、有機物で構成されたオートマタです」"
    },
    {
        "name": "ミク",
        "message": "「情報収集を目的に『マザー』によって作られ、深く繋がりを持つ、『マザー』システムの一部なのです」"
    },
    {
        "name": "ユイ",
        "message": "「つまり……？」"
    },
    {
        "message": "そこまでは、シレイさんも同じだから、実感を伴って理解していたことだけど――"
    },
    {
        "name": "ミク",
        "message": "「『マザー』の判断は、私の判断でもあるということです」"
    },
    {
        "message": "……言っている意味が、よく分からなかった。"
    },
    {
        "name": "ミク",
        "message": "「『マザー』システムは、中央の量子コンピューターも含めた、いくつもの端末の集合体――私やシレイ、その他『私達』の集合知です」"
    },
    {
        "name": "ミク",
        "message": "「その中でも、『性別統一計画』に関しては、被検体の護衛と計画監視を担当する私達……３９号と４０号の権限が大きく設定されていました」"
    },
    {
        "name": "アカリ",
        "message": "「え……っと」"
    },
    {
        "name": "ミク",
        "message": "「ようするに、私が決めたんです」"
    },
    {
        "name": "ユイ",
        "message": "「……何を、ですか？」"
    },
    {
        "name": "ミク",
        "message": "「世界に男はいらない。人類に恋など必要ないのだと……」"
    },
    {
        "name": "ユイ",
        "message": "「…………」"
    },
    {
        "message": "それは、もしかして……何かそう思うに至ったきっかけがあるとするならば。"
    },
    {
        "name": "ミク",
        "message": "「ごめんなさい……全ては、私の望みだったんです」"
    },
    {
        "name": "ミク",
        "message": "「選択肢の一つに過ぎなかった『性別統一計画』の推進も、貴女方が追われる立場になったのも……」"
    },
    {
        "name": "アカリ",
        "message": "「え、え……？　でも先輩は、『マザー』を裏切ってまで、わたし達を助けてくれて……」"
    },
    {
        "name": "ミク",
        "message": "「それもまた、私の想いの一つでした。けれど私は、ユイさんに……その、振られてしまって……心のどこかで、望んでしまいました」"
    },
    {
        "message": "アカリの視線が、戸惑いがちに僕に向けられる。"
    },
    {
        "name": "ミク",
        "message": "「哀しくて、痛くて、恥ずかしくて……何もなかったことにしてしまいたい。もう恋などしたくないと、思ってしまった」"
    },
    {
        "name": "ミク",
        "message": "「そして私のその感情が、『マザー』の判断を大きく計画の推進へと傾けたのです」"
    },
    {
        "name": "ユイ",
        "message": "「……僕のせい、ですか？」"
    },
    {
        "name": "ミク",
        "message": "「いえ……私の勝手な想いでしたから。私の責任です」"
    },
    {
        "name": "ミク",
        "message": "「想いを告げる前から、ずっと、お二人の関係を見ているのが辛かった……。割り込めそうにもなくて、どこか心の片隅で、この現実世界に嫌気が差していました」"
    },
    {
        "name": "ユイ",
        "message": "「じゃあどうして、僕達を助けたんですか。余計なことはせず、恨みを晴らせばよかったじゃないですか」"
    },
    {
        "name": "ミク",
        "message": "「失恋しても、大切な後輩には変わりませんから」"
    },
    {
        "message": "……ずるいと思った。そんな風に言われると、もう恨み言なんて言えなくなってしまう。"
    },
    {
        "name": "アカリ",
        "message": "「ミク先輩」"
    },
    {
        "message": "僕が口をつぐむと、アカリがぽつりと呼びかけた。"
    },
    {
        "name": "ミク",
        "message": "「……はい」"
    },
    {
        "name": "アカリ",
        "message": "「でも、今は違うんですよね？」"
    },
    {
        "name": "ミク",
        "message": "「…………」"
    },
    {
        "name": "アカリ",
        "message": "「わたし達が生きていて、先輩がここにいるってことは……今はもう違うってことですよね？」"
    },
    {
        "name": "ミク",
        "message": "「それは……」"
    },
    {
        "name": "アカリ",
        "message": "「先輩の気持ちで『マザー』の判断が変わっちゃうのなら、そういうことですよね？」"
    },
    {
        "message": "何か少し拗ねたような口調で、アカリが問いかける。"
    },
    {
        "name": "ミク",
        "message": "「……長い夢を、見ていました」"
    },
    {
        "message": "先輩は答えずに、そっと目を閉じて……何かの想いに浸る。"
    },
    {
        "name": "ミク",
        "message": "「夢の中でたくさん考えて、やっと吹っ切れたような気がするんです」"
    },
    {
        "name": "ミク",
        "message": "「だから……現実は、何も変わってなんかいないけど」"
    },
    {
        "message": "先輩は……ゆっくりと顔を上げて、帽子を手に取った。"
    },
    {
        "name": "ミク",
        "message": "「やっぱり、す……好きです、ユイさんのこと」"
    },
    {
        "name": "ユイ",
        "message": "「え……と……」"
    },
    {
        "name": "ミク",
        "message": "「迷惑なのは分かっています。振られたことも理解しています。それでも、私は……」"
    },
    {
        "message": "手が震えている先輩を見て、心が千々に乱される。絶対に、アカリを裏切るつもりなんてないけれど――"
    },
    {
        "name": "アカリ",
        "message": "「負けませんから」"
    },
    {
        "name": "ユイ",
        "message": "「えっ……あ、アカリ！？」"
    },
    {
        "name": "アカリ",
        "message": "「結局、先輩は諦めないってことですよね？　わたしもです」"
    },
    {
        "name": "ユイ",
        "message": "「あ、あの――」"
    },
    {
        "name": "アカリ",
        "message": "「ユイちゃんはちょっと黙ってて。気持ちがぐらぐらしてるの、見れば分かるんだから」"
    },
    {
        "name": "ユイ",
        "message": "「そんなことは――」"
    },
    {
        "name": "アカリ",
        "message": "「ないって言い切れる？」"
    },
    {
        "name": "ユイ",
        "message": "「…………黙ってます」"
    },
    {
        "message": "睨まれて、逆らえなくなってしまった。"
    },
    {
        "name": "アカリ",
        "message": "「それで、どうなんですか？ミク先輩は、もう一回振られにきたんですか？」"
    },
    {
        "name": "ミク",
        "message": "「それは……ユイさん次第で……」"
    },
    {
        "name": "アカリ",
        "message": "「というか。ミク先輩に告白されてたって、わたし知らなかったんだけど？」"
    },
    {
        "name": "ユイ",
        "message": "「そ、そんなの言えないよっ」"
    },
    {
        "name": "アカリ",
        "message": "「それ、後ろめたい気持ちがあるからだよね？」"
    },
    {
        "name": "ユイ",
        "message": "「ち、違っ……」"
    },
    {
        "message": "ミク先輩の目の前で、何故だか痴話喧嘩が始まってしまう。"
    },
    {
        "message": "そんな僕達を見て、ミク先輩は……ゆっくりと、優しい微笑みを浮かべていた。"
    },
    {
        "name": "ミク",
        "message": "「ああ……これが本物」"
    },
    {
        "message": "その言葉がどういう意味なのか、正確には分からなかった。"
    },
    {
        "message": "でも、その微笑みはとても温もりに満ちていて……思わず見とれてしまいそうになる。"
    },
    {
        "name": "ミク",
        "message": "「ユイさん、アカリさん――私も、諦めきれませんでした。もっと、恋をしてみたかった」"
    },
    {
        "name": "ミク",
        "message": "「だから戻ってきたんです。妄想の一人遊びから、現実の世界に……立ち向かいたくて」"
    },
    {
        "name": "アカリ",
        "message": "「じゃあ、勝負ですね」"
    },
    {
        "message": "対するアカリも、今度は笑顔になっていた。"
    },
    {
        "name": "ミク",
        "message": "「いいのですか？　同じ舞台に上がっても」"
    },
    {
        "name": "アカリ",
        "message": "「駄目なわけないですよ。だって――」"
    },
    {
        "message": "そしてアカリは、楽しそうに言ってのけたのだ。"
    },
    {
        "name": "アカリ",
        "message": "「だって女の子は、恋する生き物なんですから♪」"
    },
    {
        "name": "ミク",
        "message": "「……恋をするために、生まれてきた」"
    },
    {
        "name": "アカリ",
        "message": "「はい！　だから、負けません！」"
    },
    {
        "name": "ミク",
        "message": "「私も、です」"
    },
    {
        "message": "……ていうか、なんだこれ。いつの間にか、二人で分かり合ってるみたいだけど。"
    },
    {
        "name": "ユイ",
        "message": "「あ、あの……僕を置き去りにして話を進めないで欲しいというか」"
    },
    {
        "name": "アカリ",
        "message": "「あのね、ユイちゃん」"
    },
    {
        "name": "ユイ",
        "message": "「は、はいっ」"
    },
    {
        "name": "アカリ",
        "message": "「わたし思うんだけど、今どき一人しか好きになっちゃいけないってことはなくない？」"
    },
    {
        "name": "ユイ",
        "message": "「……なくないことはない、ような」"
    },
    {
        "name": "アカリ",
        "message": "「昔みたいな結婚制度もなくなったし、子供作るのもみんな人気のイケメンしか選ばないのに？」"
    },
    {
        "message": "そう言われると、確かに一夫一婦制は前世紀までの価値観でしかない……とはいえ。"
    },
    {
        "name": "アカリ",
        "message": "「だから、とりあえず今大切なのはひとつだけ」"
    },
    {
        "message": "まっすぐに、自信に満ちた瞳が向けられてくる。"
    },
    {
        "name": "アカリ",
        "message": "「ユイちゃんは、ミク先輩のこと……好き？」"
    },
    {
        "name": "ミク",
        "message": "「…………」"
    },
    {
        "message": "敵わないな、と思った。"
    },
    {
        "message": "僕なんかよりよっぽど強くて、聖母みたいな女の子から言われたら、もう嘘なんてつけなくなってしまう。"
    },
    {
        "name": "ミク",
        "message": "「……ユイ、さん」"
    },
    {
        "message": "だから、緊張して待っているミク先輩に……僕は返事をした。"
    },
    {
        "name": "ユイ",
        "message": "「その……」"
    },
    {
        "message": "一度は断った手前、気まずくて、蚊の鳴くような声で。"
    },
    {
        "name": "ユイ",
        "message": "「………………き、です」"
    },
    {
        "name": "ミク",
        "message": "「…………」"
    },
    {
        "name": "ユイ",
        "message": "「い、一番好きなのは、アカリなんですけど……！」"
    },
    {
        "name": "ユイ",
        "message": "「ミク先輩のことも……好き、です」"
    },
    {
        "message": "言っていて、ようするにただの二股だって、改めて思った。"
    },
    {
        "name": "ユイ",
        "message": "「ねえ、これ普通に最低男じゃない！？　処刑とかされない！？」"
    },
    {
        "name": "アカリ",
        "message": "「あははっ、どうだろう？」"
    },
    {
        "name": "ユイ",
        "message": "「アカリ！？」"
    },
    {
        "message": "苦悶する僕の隣で、アカリがくすくすと笑っていた。"
    },
    {
        "name": "ミク",
        "message": "「それは、私も……ですよ」"
    },
    {
        "message": "そして、僕の正面では――"
    },
    {
        "name": "ミク",
        "message": "「本当にっ……最低、ですね！」"
    },
    {
        "message": "一人の恋する女の子が、幸せそうに笑っていた。"
    }
]